Metadata-Version: 2.4
Name: fastapi-filters
Version: 0.3.1
Summary: fastapi-filters
Author-email: Yurii Karabas <1998uriyyo@gmail.com>
License-Expression: MIT
License-File: LICENSE
Classifier: Operating System :: OS Independent
Classifier: Programming Language :: Python
Classifier: Programming Language :: Python :: 3
Classifier: Programming Language :: Python :: 3 :: Only
Classifier: Programming Language :: Python :: 3.10
Classifier: Programming Language :: Python :: 3.11
Classifier: Programming Language :: Python :: 3.12
Classifier: Programming Language :: Python :: 3.13
Requires-Python: <4.0,>=3.10
Requires-Dist: fastapi>=0.100.0
Requires-Dist: pydantic>=2.0.0
Requires-Dist: typing-extensions>=4.4.0
Requires-Dist: typing-inspect>=0.4.0
Provides-Extra: beanie
Requires-Dist: beanie>=1.29.0; extra == 'beanie'
Provides-Extra: raw-sql
Requires-Dist: sqlalchemy>=2.0.0; extra == 'raw-sql'
Provides-Extra: sqlalchemy
Requires-Dist: sqlalchemy>=2.0.0; extra == 'sqlalchemy'
Provides-Extra: tortoise-orm
Requires-Dist: tortoise-orm<0.26,>=0.20; extra == 'tortoise-orm'
